codec.vhd
library ieee, std;
use ieee.std_logic_1164.all;
use ieee.numeric_std.all;
use std.textio.all;

entity codec is
    port(
        interrupt: in std_logic; -- Interrupt signal
        read_signal: in std_logic; -- Read signal
        write_signal: in std_logic; -- Write signal
        valid: out std_logic; -- Valid signal

    -- Byte written to codec
        codec_data_in : in std_logic_vector(7 downto 0);
    -- Byte read from codec
        codec_data_out : out std_logic_vector(7 downto 0)
    );
end entity;

architecture behavioral of codec is
    file arq_r : text open read_mode is "firmware.bin";
    file arq_w: text open write_mode is "escrita.txt"; 
begin
    in_out: process is
        variable write_aux : Bit_vector(7 downto 0);
        variable rreeaad_char : Bit_vector(7 downto 0);
        variable write_line, read_line : line; 
    begin
        if read_signal = '1' and write_signal = '0' and rising_edge(interrupt) then
            readline(arq_r, read_line);
            read(read_line, rreeaad_char);
            codec_data_out <= to_stdlogicvector(rreeaad_char);
            valid <= '1';
            wait for 500 ps;
            valid <= '0';
        end if;
        if read_signal = '0' and write_signal = '1' and rising_edge(interrupt) then
            write(write_line, to_bitvector(codec_data_in));
            writeline(arq_w, write_line);
            valid <= '1';
            wait for 500 ps;
            valid <= '0';
        end if;
        wait on interrupt;
    end process;
end architecture;

codec_tb.vhd
library ieee;
use ieee.std_logic_1164.all;
use ieee.numeric_std.all;

entity codec_tb is
end entity;

architecture mixed of codec_tb is
    -- signals declaration
    signal interrupt, read_signal, write_signal, valid : std_logic;
    signal codec_data_in, codec_data_out :  std_logic_vector(7 downto 0);
begin
    mem_t:  entity work.codec(behavioral)
            port map (interrupt, read_signal, write_signal, valid, codec_data_in, codec_data_out);

    testing_memory: process is
        type line_tv is record
            inte, rd_s, wr_s, v : std_logic;
            c_dt_in, c_dt_out : std_logic_vector(7 downto 0);
        end record;
        type vet_l_tv is array (0 to 23) of line_tv;
        constant tb : vet_l_tv :=
        --   IN  read  write valid CodInput   CodOut
        (   ('0', '0', '0', '0', "00000000", "00000000" ),
            ('1', '1', '0', '1', "00000000", "10000001" ),
            ('0', '0', '0', '0', "00000000", "00000000" ), -- pulse simulation
            ('1', '1', '0', '1', "00000000", "01111110" ),
            ('0', '0', '0', '0', "00000000", "00000000" ), -- pulse simulation
            ('1', '1', '0', '1', "00000000", "11110000" ),
            ('0', '0', '0', '0', "00000000", "00000000" ), -- pulse simulation
            ('1', '1', '0', '1', "00000000", "00001111" ),
            ('0', '0', '0', '0', "00000000", "00000000" ), -- pulse simulation
            ('1', '1', '0', '1', "00000000", "10101010" ),
            ('0', '0', '0', '0', "00000000", "00000000" ), -- pulse simulation
            ('1', '1', '0', '1', "00000000", "01010101" ),
            ('0', '0', '0', '0', "00000000", "00000000" ), -- pulse simulation
            ('1', '0', '1', '1', "10000001", "00000000" ),
            ('0', '0', '0', '0', "00000000", "00000000" ), -- pulse simulation
            ('1', '0', '1', '1', "01111110", "00000000" ),
            ('0', '0', '0', '0', "00000000", "00000000" ), -- pulse simulation
            ('1', '0', '1', '1', "11110000", "00000000" ),
            ('0', '0', '0', '0', "00000000", "00000000" ), -- pulse simulation
            ('1', '0', '1', '1', "00001111", "00000000" ),
            ('0', '0', '0', '0', "00000000", "00000000" ), -- pulse simulation
            ('1', '0', '1', '1', "10101010", "00000000" ),
            ('0', '0', '0', '0', "00000000", "00000000" ), -- pulse simulation
            ('1', '0', '1', '1', "01010101", "00000000" ));
    begin
        for i in tb'range loop
            interrupt <= tb(i).inte;
            read_signal <= tb(i).rd_s;
            write_signal <= tb(i).wr_s;
            codec_data_in <= tb(i).c_dt_in;
      
            wait for 2 ns;
            if tb(i).wr_s = '0' and tb(i).inte = '1' then
                assert codec_data_out = tb(i).c_dt_out
                report "YAMETE KUDASAI" & integer'image(i)
                severity error;
            end if; 
        end loop;
        report "Fim dos Testes";
        wait;
    end process;
end architecture;

codec_tb.vcd
$date
  Sat Oct 15 21:14:03 2022
$end
$version
  GHDL v0
$end
$timescale
  1 fs
$end
$scope module standard $end
$upscope $end
$scope module std_logic_1164 $end
$upscope $end
$scope module numeric_std $end
$upscope $end
$scope module textio $end
$upscope $end
$scope module codec_tb $end
$var reg 1 ! interrupt $end
$var reg 1 " read_signal $end
$var reg 1 # write_signal $end
$var reg 1 $ valid $end
$var reg 8 % codec_data_in[7:0] $end
$var reg 8 & codec_data_out[7:0] $end
$scope module mem_t $end
$var reg 1 ' interrupt $end
$var reg 1 ( read_signal $end
$var reg 1 ) write_signal $end
$var reg 1 * valid $end
$var reg 8 + codec_data_in[7:0] $end
$var reg 8 , codec_data_out[7:0] $end
$upscope $end
$upscope $end
$enddefinitions $end
#0
0!
0"
0#
U$
b00000000 %
bUUUUUUUU &
0'
0(
0)
U*
b00000000 +
bUUUUUUUU ,
#2000000
1!
1"
1$
b10000001 &
1'
1(
1*
b10000001 ,
#4000000
0!
0"
0'
0(
#6000000
1!
1"
b01111110 &
1'
1(
b01111110 ,
#8000000
0!
0"
0'
0(
#10000000
1!
1"
b11110000 &
1'
1(
b11110000 ,
#12000000
0!
0"
0'
0(
#14000000
1!
1"
b00001111 &
1'
1(
b00001111 ,
#16000000
0!
0"
0'
0(
#18000000
1!
1"
b10101010 &
1'
1(
b10101010 ,
#20000000
0!
0"
0'
0(
#22000000
1!
1"
b01010101 &
1'
1(
b01010101 ,
#24000000
0!
0"
0'
0(
#26000000
1!
1#
b10000001 %
1'
1)
b10000001 +
#28000000
0!
0#
b00000000 %
0'
0)
b00000000 +
#30000000
1!
1#
b01111110 %
1'
1)
b01111110 +
#32000000
0!
0#
b00000000 %
0'
0)
b00000000 +
#34000000
1!
1#
b11110000 %
1'
1)
b11110000 +
#36000000
0!
0#
b00000000 %
0'
0)
b00000000 +
#38000000
1!
1#
b00001111 %
1'
1)
b00001111 +
#40000000
0!
0#
b00000000 %
0'
0)
b00000000 +
#42000000
1!
1#
b10101010 %
1'
1)
b10101010 +
#44000000
0!
0#
b00000000 %
0'
0)
b00000000 +
#46000000
1!
1#
b01010101 %
1'
1)
b01010101 +
