memory.vhd
library ieee;
use ieee.std_logic_1164.all;
use ieee.numeric_std.all;

entity memory is
    generic(
        addr_width: natural := 16; -- Memory Address Width (in bits)
        data_width: natural := 8 -- Data Width (in bits)
    );

port(
    clock: in std_logic; -- Clock signal; Write on Falling-Edge
    data_read : in std_logic; -- When '1', read data from memory
    data_write: in std_logic; -- When '1', write data to memory
 -- Data address given to memory
    data_addr : in std_logic_vector(addr_width-1 downto 0);
 -- Data sent from memory when data_read = '1' and data_write = '0'
    data_in : in std_logic_vector(data_width-1 downto 0);
 -- Data sent to memory when data_read = '0' and data_write = '1'
    data_out : out std_logic_vector((data_width*4)-1 downto 0)
);
end entity;

architecture behavioral of memory is
    -- create a new type named something near signal little_data_vet : std_logic_vector(data_width - 1 down to 0);
    -- create a new variable data_vet : little_data_vet type (addr_width - 1 downto 0);
    -- aparently it doesn't need to be first a type because we're
    -- declaring a mult dimensional vector. hope it works
    -- needs to change the address range (first dimension) 
    type data_vet_t is array (2**addr_width - 1 downto 0) of std_logic_vector(data_width - 1 downto 0); 
    signal data_vet : data_vet_t := (others => "00000000");
    signal data_help : std_logic_vector(data_width - 1 downto 0) := (others => '0');
begin
    whole_p: process (clock, data_read, data_write, data_addr) is
        begin
            -- the read part is almost compleated, it has right casts for the range of the first dimension
            -- now, I need to see if it is going to get que right slice of each part
            if data_read = '1' and data_write = '0' then
                -- d 4x 7 a 0                      d 7 a 0
                if to_integer(unsigned(data_addr)) <= (2**addr_width - 4) then
                    data_out(data_width - 1 downto 0) <= data_vet(to_integer(unsigned(data_addr)));
                    data_out((data_width*2) - 1 downto data_width) <= data_vet(to_integer(unsigned(data_addr) + 1));
                    data_out((data_width*3) - 1 downto data_width*2) <= data_vet(to_integer(unsigned(data_addr) + 2));
                    data_out((data_width*4) - 1 downto data_width*3) <= data_vet(to_integer(unsigned(data_addr) + 3));
                elsif to_integer(unsigned(data_addr)) <= (2**addr_width - 3) then
                    data_out(data_width - 1 downto 0) <= data_vet(to_integer(unsigned(data_addr)));
                    data_out((data_width*2) - 1 downto data_width) <= data_vet(to_integer(unsigned(data_addr) + 1));
                    data_out((data_width*3) - 1 downto data_width*2) <= data_vet(to_integer(unsigned(data_addr) + 2));
                    data_out((data_width*4) - 1 downto data_width*3) <= data_help;
                elsif to_integer(unsigned(data_addr)) <= (2**addr_width - 2) then
                    data_out(data_width - 1 downto 0) <= data_vet(to_integer(unsigned(data_addr)));
                    data_out((data_width*2) - 1 downto data_width) <= data_vet(to_integer(unsigned(data_addr) + 1));
                    data_out((data_width*3) - 1 downto data_width*2) <= data_help;
                    data_out((data_width*4) - 1 downto data_width*3) <= data_help;
                else
                    data_out(data_width - 1 downto 0) <= data_vet(to_integer(unsigned(data_addr)));
                    data_out((data_width*2) - 1 downto data_width) <= data_help;
                    data_out((data_width*3) - 1 downto data_width*2) <= data_help;
                    data_out((data_width*4) - 1 downto data_width*3) <= data_help;              
                end if;
            elsif falling_edge(clock) and data_read = '0' and data_write = '1' then
                data_vet(to_integer(unsigned(data_addr))) <= data_in;
            end if;
        end process;
end architecture;

mem_tb.vhd
library ieee;
use ieee.std_logic_1164.all;
use ieee.numeric_std.all;

entity mem_tb is
end entity;

architecture mixed of mem_tb is
    -- signals declaration
    signal addr_width: natural := 16; -- Memory Address Width (in bits)
    signal data_width: natural := 8; -- Data Width (in bits)
    signal clock, data_read, data_write : std_logic;
    signal data_addr :  std_logic_vector(addr_width-1 downto 0);
    signal data_in :    std_logic_vector(data_width-1 downto 0);
    signal data_out :   std_logic_vector((data_width*4)-1 downto 0); -- possivel others
begin
    mem_t:  entity work.memory(behavioral)
            generic map (addr_width, data_width)
            port map (clock, data_read, data_write, data_addr, data_in, data_out);

    testing_memory: process is
        type line_tv is record
            ck, dt_r, dt_w : std_logic;
            dt_addr : std_logic_vector(addr_width-1 downto 0);
            dt_in   : std_logic_vector(data_width-1 downto 0);
            dt_out  : std_logic_vector((data_width*4)-1 downto 0);
        end record;
        type vet_l_tv is array (0 to 25) of line_tv;
        constant tb : vet_l_tv :=
        -- ck read write      address           input                 output
        ( ('1', '1', '0', "0000000000000000", "00000000", "00000000000000000000000000000000"),
          ('0', '0', '1', "0000000000000000", "10000001", "00000000000000000000000000000000"),
          ('1', '1', '0', "0000000000000000", "10000001", "00000000000000000000000010000001"),
          ('0', '0', '1', "0000000000000001", "01111110", "00000000000000000000000010000001"),
          ('1', '1', '0', "0000000000000000", "01111110", "00000000000000000111111010000001"),
          ('0', '0', '1', "0000000000000010", "10101010", "00000000000000000111111010000001"),
          ('1', '1', '0', "0000000000000000", "10101010", "00000000101010100111111010000001"),
          ('0', '0', '1', "0000000000000011", "10000000", "00000000101010100111111010000001"),
          ('1', '1', '0', "0000000000000000", "00000000", "10000000101010100111111010000001"),
          ('0', '1', '0', "1111111111111100", "00000000", "00000000000000000000000000000000"),
          ('1', '1', '0', "1111111111111100", "10000000", "00000000000000000000000000000000"),
          ('0', '0', '1', "1111111111111100", "10000000", "00000000000000000000000000000000"),
          ('1', '1', '0', "1111111111111100", "10000000", "00000000000000000000000010000000"),
          ('0', '0', '1', "1111111111111101", "11110000", "00000000000000000000000010000000"),
          ('1', '1', '0', "1111111111111100", "11110000", "00000000000000001111000010000000"),
          ('0', '0', '1', "1111111111111110", "00001111", "00000000000000001111000010000000"),
          ('1', '1', '0', "1111111111111100", "00001111", "00000000000011111111000010000000"),
          ('0', '0', '1', "1111111111111111", "10000001", "00000000000011111111000010000000"),
          ('1', '1', '0', "1111111111111100", "10000001", "10000001000011111111000010000000"),
          ('1', '0', '0', "1111111111111100", "10000001", "10000001000011111111000010000000"),
          ('1', '1', '0', "0000000000000000", "00000000", "10000000101010100111111010000001"),
          ('1', '0', '0', "0000000000000000", "00000000", "10000000101010100111111010000001"),
          ('1', '1', '0', "1111111111111100", "10000001", "10000001000011111111000010000000"),
          ('0', '1', '0', "1111111111111101", "00000000", "00000000100000010000111111110000"),
          ('1', '1', '0', "1111111111111110", "00000000", "00000000000000001000000100001111"),
          ('0', '1', '0', "1111111111111111", "00000000", "00000000000000000000000010000001"));
    begin
        for i in tb'range loop
            clock <= tb(i).ck;
            data_read <= tb(i).dt_r;
            data_write <= tb(i).dt_w;
            data_addr <= tb(i).dt_addr;
            data_in <= tb(i).dt_in;
            wait for 2 ns;
            assert data_out = tb(i).dt_out
            report "i:" & integer'image(i) 
            severity error;
        end loop;
        report "Fim dos Testes";
        wait;
    end process;
end architecture;

mem_tb.vcd
$date
  Sat Oct 15 21:13:14 2022
$end
$version
  GHDL v0
$end
$timescale
  1 fs
$end
$scope module standard $end
$upscope $end
$scope module std_logic_1164 $end
$upscope $end
$scope module numeric_std $end
$upscope $end
$scope module mem_tb $end
$var integer 32 ! addr_width $end
$var integer 32 " data_width $end
$var reg 1 # clock $end
$var reg 1 $ data_read $end
$var reg 1 % data_write $end
$var reg 16 & data_addr[15:0] $end
$var reg 8 ' data_in[7:0] $end
$var reg 32 ( data_out[31:0] $end
$scope module mem_t $end
$var reg 1 ) clock $end
$var reg 1 * data_read $end
$var reg 1 + data_write $end
$var reg 16 , data_addr[15:0] $end
$var reg 8 - data_in[7:0] $end
$var reg 32 . data_out[31:0] $end
$comment data_vet is not handled $end
$var reg 8 / data_help[7:0] $end
$upscope $end
$upscope $end
$enddefinitions $end
#0
b10000 !
b1000 "
1#
1$
0%
b0000000000000000 &
b00000000 '
b00000000000000000000000000000000 (
1)
1*
0+
b0000000000000000 ,
b00000000 -
b00000000000000000000000000000000 .
b00000000 /
#2000000
0#
0$
1%
b10000001 '
0)
0*
1+
b10000001 -
#4000000
1#
1$
0%
b00000000000000000000000010000001 (
1)
1*
0+
b00000000000000000000000010000001 .
#6000000
0#
0$
1%
b0000000000000001 &
b01111110 '
0)
0*
1+
b0000000000000001 ,
b01111110 -
#8000000
1#
1$
0%
b0000000000000000 &
b00000000000000000111111010000001 (
1)
1*
0+
b0000000000000000 ,
b00000000000000000111111010000001 .
#10000000
0#
0$
1%
b0000000000000010 &
b10101010 '
0)
0*
1+
b0000000000000010 ,
b10101010 -
#12000000
1#
1$
0%
b0000000000000000 &
b00000000101010100111111010000001 (
1)
1*
0+
b0000000000000000 ,
b00000000101010100111111010000001 .
#14000000
0#
0$
1%
b0000000000000011 &
b10000000 '
0)
0*
1+
b0000000000000011 ,
b10000000 -
#16000000
1#
1$
0%
b0000000000000000 &
b00000000 '
b10000000101010100111111010000001 (
1)
1*
0+
b0000000000000000 ,
b00000000 -
b10000000101010100111111010000001 .
#18000000
0#
b1111111111111100 &
b00000000000000000000000000000000 (
0)
b1111111111111100 ,
b00000000000000000000000000000000 .
#20000000
1#
b10000000 '
1)
b10000000 -
#22000000
0#
0$
1%
0)
0*
1+
#24000000
1#
1$
0%
b00000000000000000000000010000000 (
1)
1*
0+
b00000000000000000000000010000000 .
#26000000
0#
0$
1%
b1111111111111101 &
b11110000 '
0)
0*
1+
b1111111111111101 ,
b11110000 -
#28000000
1#
1$
0%
b1111111111111100 &
b00000000000000001111000010000000 (
1)
1*
0+
b1111111111111100 ,
b00000000000000001111000010000000 .
#30000000
0#
0$
1%
b1111111111111110 &
b00001111 '
0)
0*
1+
b1111111111111110 ,
b00001111 -
#32000000
1#
1$
0%
b1111111111111100 &
b00000000000011111111000010000000 (
1)
1*
0+
b1111111111111100 ,
b00000000000011111111000010000000 .
#34000000
0#
0$
1%
b1111111111111111 &
b10000001 '
0)
0*
1+
b1111111111111111 ,
b10000001 -
#36000000
1#
1$
0%
b1111111111111100 &
b10000001000011111111000010000000 (
1)
1*
0+
b1111111111111100 ,
b10000001000011111111000010000000 .
#38000000
0$
0*
#40000000
1$
b0000000000000000 &
b00000000 '
b10000000101010100111111010000001 (
1*
b0000000000000000 ,
b00000000 -
b10000000101010100111111010000001 .
#42000000
0$
0*
#44000000
1$
b1111111111111100 &
b10000001 '
b10000001000011111111000010000000 (
1*
b1111111111111100 ,
b10000001 -
b10000001000011111111000010000000 .
#46000000
0#
b1111111111111101 &
b00000000 '
b00000000100000010000111111110000 (
0)
b1111111111111101 ,
b00000000 -
b00000000100000010000111111110000 .
#48000000
1#
b1111111111111110 &
b00000000000000001000000100001111 (
1)
b1111111111111110 ,
b00000000000000001000000100001111 .
#50000000
0#
b1111111111111111 &
b00000000000000000000000010000001 (
0)
b1111111111111111 ,
b00000000000000000000000010000001 .
